mlx90614/__init__.py
mlx90614/mlx90614.py
PyMLX90614-0.0.4.dist-info/LICENSE
PyMLX90614-0.0.4.dist-info/METADATA
PyMLX90614-0.0.4.dist-info/WHEEL
PyMLX90614-0.0.4.dist-info/top_level.txt
PyMLX90614-0.0.4.dist-info/RECORD
